{
  "id": "个人博客/Java实现批量重命名文件",
  "title": "Java实现批量重命名文件",
  "description": "前言",
  "source": "@site/docs/个人博客/Java实现批量重命名文件.md",
  "sourceDirName": "个人博客",
  "slug": "/个人博客/Java实现批量重命名文件",
  "permalink": "/docs/个人博客/Java实现批量重命名文件",
  "draft": false,
  "unlisted": false,
  "editUrl": "https://github.com/你的github用户名/my-docs/edit/main/docs/个人博客/Java实现批量重命名文件.md",
  "tags": [],
  "version": "current",
  "frontMatter": {},
  "sidebar": "tutorialSidebar",
  "previous": {
    "title": "Java代码执行顺序",
    "permalink": "/docs/个人博客/Java代码执行顺序"
  },
  "next": {
    "title": "Java封装同步锁",
    "permalink": "/docs/个人博客/Java封装同步锁"
  }
}