{
  "id": "谷粒学院在线教育项目/day14/名师页面静态效果整合",
  "title": "一、列表页面",
  "description": "创建 pages/teacher/index.vue",
  "source": "@site/docs/谷粒学院在线教育项目/day14/01-名师页面静态效果整合.md",
  "sourceDirName": "谷粒学院在线教育项目/day14",
  "slug": "/谷粒学院在线教育项目/day14/名师页面静态效果整合",
  "permalink": "/docs/谷粒学院在线教育项目/day14/名师页面静态效果整合",
  "draft": false,
  "unlisted": false,
  "editUrl": "https://github.com/你的github用户名/my-docs/edit/main/docs/谷粒学院在线教育项目/day14/01-名师页面静态效果整合.md",
  "tags": [],
  "version": "current",
  "sidebarPosition": 1,
  "frontMatter": {},
  "sidebar": "tutorialSidebar",
  "previous": {
    "title": "一、什么是OAuth2",
    "permalink": "/docs/谷粒学院在线教育项目/day13/02-02-OAuth2的正式定义"
  },
  "next": {
    "title": "一、后端",
    "permalink": "/docs/谷粒学院在线教育项目/day14/讲师列表页"
  }
}